llama_tool_parser_native-0.0.3.dist-info/METADATA
llama_tool_parser_native-0.0.3.dist-info/WHEEL
llama_tool_parser_native/__init__.py
llama_tool_parser_native/llama_tool_parser_native.abi3.so
llama_tool_parser_native-0.0.3.dist-info/RECORD
